webopencv/__init__.py
webopencv/aio.py
webopencv/app.py
webopencv/flsk.py
webopencv/transforms.py
webopencv/utils.py
webopencv/static/client.js
webopencv/templates/index.html
webopencv-0.0.4.dist-info/LICENSE
webopencv-0.0.4.dist-info/METADATA
webopencv-0.0.4.dist-info/WHEEL
webopencv-0.0.4.dist-info/top_level.txt
webopencv-0.0.4.dist-info/RECORD
