Metadata-Version: 2.1
Name: webopencv
Version: 0.0.4
Summary: Stream live video feed from a webpage to a server-side python openCV script
Home-page: https://github.com/alvinwan/webopencv
Author: Alvin Wan
Author-email: hi@alvinwan.com
License: BSD
Project-URL: Bug Tracker, https://github.com/alvinwan/webopencv/issues
Platform: UNKNOWN
Classifier: Programming Language :: Python :: 3
Classifier: License :: OSI Approved :: MIT License
Classifier: Operating System :: OS Independent
Requires-Python: >=3.6
License-File: LICENSE
Requires-Dist: aiohttp (==3.7.4.post0)
Requires-Dist: aiortc (==1.2.1)
Requires-Dist: opencv-python (==4.5.3.56)
Requires-Dist: flask (==2.0.1)
Requires-Dist: flask[async]
Requires-Dist: jinja2 (==3.0.1)
